COPYING
COPYING.LESSER
MANIFEST.in
README.rst
setup.cfg
setup.py
versioneer.py
libaio/__init__.py
libaio/_version.py
libaio/eventfd.py
libaio/ioprio.py
libaio/libaio.py
libaio/linux_fs.py
libaio/test.py
libaio.egg-info/PKG-INFO
libaio.egg-info/SOURCES.txt
libaio.egg-info/dependency_links.txt
libaio.egg-info/top_level.txt
libaio.egg-info/zip-safe