Metadata-Version: 2.4
Name: libaio
Version: 0.9.4
Summary: Linux AIO API wrapper
Home-page: http://github.com/vpelletier/python-libaio
Author: Vincent Pelletier
Author-email: plr.vincent@gmail.com
License: LGPLv3+
Keywords: linux aio libaio
Platform: linux
Classifier: Intended Audience :: Developers
Classifier: License :: OSI Approved :: GNU Lesser General Public License v3 or later (LGPLv3+)
Classifier: Operating System :: POSIX :: Linux
Classifier: Programming Language :: Python :: 2.7
Classifier: Programming Language :: Python :: 3
Classifier: Programming Language :: Python :: Implementation :: CPython
Classifier: Programming Language :: Python :: Implementation :: PyPy
Classifier: Topic :: Software Development :: Libraries
License-File: COPYING
License-File: COPYING.LESSER
Dynamic: author
Dynamic: author-email
Dynamic: classifier
Dynamic: description
Dynamic: description-content-type
Dynamic: home-page
Dynamic: keywords
Dynamic: license
Dynamic: license-file
Dynamic: platform
Dynamic: summary
